digit_index/__init__.py
digit_index-1.0.dist-info/LICENSE
digit_index-1.0.dist-info/METADATA
digit_index-1.0.dist-info/WHEEL
digit_index-1.0.dist-info/top_level.txt
digit_index-1.0.dist-info/RECORD
