Metadata-Version: 2.1
Name: digit-index
Version: 1.0
Summary: Package for effectively finding digit on certain index in infinite number string
Home-page: https://github.com/KonyshevArtem/digit-index
Author: Artem Konyshev
Author-email: konyshev.ar@gmail.com
License: UNKNOWN
Platform: UNKNOWN
Classifier: Programming Language :: Python :: 3
Classifier: License :: OSI Approved :: MIT License
Classifier: Operating System :: OS Independent
Requires-Python: >=3.0
